algowalk/__init__.py
algowalk/algo_selector/__init__.py
algowalk/classifier/__init__.py
algowalk/cli_interface/__init__.py
algowalk/feedback_loop/__init__.py
algowalk/model_manager/__init__.py
algowalk/problem_parser/__init__.py
algowalk/pseudocode_gen/__init__.py
algowalk/solver_engine/__init__.py
algowalk/step_planner/__init__.py
algowalk/test/__init__.py
algowalk/training/__init__.py
algowalk/utils/__init__.py
algowalk/visualizer/__init__.py
beta_algowalk-1.0.1.dist-info/licenses/LICENSE
beta_algowalk-1.0.1.dist-info/METADATA
beta_algowalk-1.0.1.dist-info/WHEEL
beta_algowalk-1.0.1.dist-info/top_level.txt
beta_algowalk-1.0.1.dist-info/RECORD
