Metadata-Version: 2.4
Name: beta_algoWalk
Version: 1.0.1
Summary: A helpful library for developers and learners to understand the working of algorithms and data structures.
Home-page: https://github.com/Kasturing/kasturing_lib
Author: @Kasturing
License: Apache Software License 2.0
Requires-Python: >=3.7
License-File: LICENSE
Requires-Dist: numpy>=1.18
Requires-Dist: pandas>=1.0
Requires-Dist: plotly>=5.0
Dynamic: author
Dynamic: description
Dynamic: description-content-type
Dynamic: home-page
Dynamic: license
Dynamic: license-file
Dynamic: requires-dist
Dynamic: requires-python
Dynamic: summary
